django_generate_series_cte/__init__.py
django_generate_series_cte/apps.py
django_generate_series_cte/exceptions.py
django_generate_series_cte/models.py
django_generate_series_cte-0.4.10.dist-info/LICENSE
django_generate_series_cte-0.4.10.dist-info/WHEEL
django_generate_series_cte-0.4.10.dist-info/METADATA
django_generate_series_cte-0.4.10.dist-info/RECORD
