Metadata-Version: 2.1
Name: django-generate-series-cte
Version: 0.4.10
Summary: Use Postgres' generate_series to create sequences with Django's ORM
Home-page: https://github.com/jacklinke/django-generate-series/
License: Apache-2.0
Keywords: graph,tree,dag,network,directed
Author: Jack Linke
Author-email: jack@watervize.com
Requires-Python: >=3.7,<4.0
Classifier: Development Status :: 3 - Alpha
Classifier: Environment :: Web Environment
Classifier: Framework :: Django
Classifier: Framework :: Django :: 2.2
Classifier: Framework :: Django :: 3.0
Classifier: Framework :: Django :: 3.1
Classifier: Framework :: Django :: 3.2
Classifier: Framework :: Django :: 4.0
Classifier: Intended Audience :: Developers
Classifier: License :: OSI Approved :: Apache Software License
Classifier: Operating System :: OS Independent
Classifier: Programming Language :: Python
Classifier: Programming Language :: Python :: 3
Classifier: Programming Language :: Python :: 3.7
Classifier: Programming Language :: Python :: 3.8
Classifier: Programming Language :: Python :: 3.9
Classifier: Programming Language :: Python :: 3.10
Classifier: Programming Language :: Python :: 3.10
Classifier: Programming Language :: Python :: 3.7
Classifier: Programming Language :: Python :: 3.8
Classifier: Programming Language :: Python :: 3.9
Classifier: Topic :: Database
Classifier: Topic :: Software Development :: Libraries
Classifier: Topic :: Utilities
Requires-Dist: django (>=4.0,<5.0)
Requires-Dist: pydantic (>=1.8,<2.0)
Project-URL: Documentation, https://django-generate-series.readthedocs.io/en/latest/
Project-URL: Repository, https://github.com/jacklinke/django-generate-series/
